<?xml version="1.0" encoding="windows-1252"?>
<DatosZona><MODULE_RESULT><Field name="Codigo">56</Field><Field name="Localidad">Arica</Field><Field name="Cod_Oficina">56</Field><Field name="Direccion">21 de Mayo 402</Field><Field name="Codigo_postal"/><Field name="Telefono">58-2269636</Field><Field name="Desplazado"/><Field name="Nombre_Oficina">Arica</Field><Field name="Latitud">-18.4790066</Field><Field name="Longitud">-70.3182034</Field><Field name="Distancia">0</Field><Field name="Numero_Cajeros">2</Field><Field name="Horario"/><Field name="Nom_Provincia">ARICA Y PARINACOTA</Field><Field name="Tipo_Oficina">P</Field><Field name="Numero_BancoFacil">1</Field><Field name="Tipo_Cajero"/><Field name="Telefono_Asociado"/></MODULE_RESULT><MODULE_RESULT><Field name="Codigo">309</Field><Field name="Localidad">Antofagasta</Field><Field name="Cod_Oficina">309</Field><Field name="Direccion">San Martín 2688</Field><Field name="Codigo_postal"/><Field name="Telefono">55-2645425</Field><Field name="Desplazado"/><Field name="Nombre_Oficina">Antofagasta Premium</Field><Field name="Latitud">-23.6466492</Field><Field name="Longitud">-70.3972433</Field><Field name="Distancia">516,8247028454</Field><Field name="Numero_Cajeros">0</Field><Field name="Horario"/><Field name="Nom_Provincia">ANTOFAGASTA</Field><Field name="Tipo_Oficina">P</Field><Field name="Numero_BancoFacil">0</Field><Field name="Tipo_Cajero"/><Field name="Telefono_Asociado"/></MODULE_RESULT><MODULE_RESULT><Field name="Codigo">51</Field><Field name="Localidad">Antofagasta</Field><Field name="Cod_Oficina">51</Field><Field name="Direccion">San Martín 2688</Field><Field name="Codigo_postal"/><Field name="Telefono">55-2645291</Field><Field name="Desplazado"/><Field name="Nombre_Oficina">Antofagasta</Field><Field name="Latitud">-23.6466492</Field><Field name="Longitud">-70.3972433</Field><Field name="Distancia">516,8247028454</Field><Field name="Numero_Cajeros">2</Field><Field name="Horario"/><Field name="Nom_Provincia">ANTOFAGASTA</Field><Field name="Tipo_Oficina">P</Field><Field name="Numero_BancoFacil">1</Field><Field name="Tipo_Cajero"/><Field name="Telefono_Asociado"/></MODULE_RESULT><MODULE_RESULT><Field name="Codigo">223</Field><Field name="Localidad">Antofagasta</Field><Field name="Cod_Oficina">223</Field><Field name="Direccion">José Miguel Carrera 1613</Field><Field name="Codigo_postal"/><Field name="Telefono">55-2645207</Field><Field name="Desplazado"/><Field name="Nombre_Oficina">Antofagasta Parque Brasil</Field><Field name="Latitud">-23.6601373</Field><Field name="Longitud">-70.4019498</Field><Field name="Distancia">518,1807482915</Field><Field name="Numero_Cajeros">2</Field><Field name="Horario"/><Field name="Nom_Provincia">ANTOFAGASTA</Field><Field name="Tipo_Oficina">P</Field><Field name="Numero_BancoFacil">1</Field><Field name="Tipo_Cajero"/><Field name="Telefono_Asociado"/></MODULE_RESULT><MODULE_RESULT><Field name="Codigo">49</Field><Field name="Localidad">Copiapó</Field><Field name="Cod_Oficina">49</Field><Field name="Direccion">O'Higgins 640</Field><Field name="Codigo_postal"/><Field name="Telefono">52-2245713</Field><Field name="Desplazado"/><Field name="Nombre_Oficina">Copiapó</Field><Field name="Latitud">-27.3669951</Field><Field name="Longitud">-70.3329806</Field><Field name="Distancia">888,8000784303</Field><Field name="Numero_Cajeros">2</Field><Field name="Horario"/><Field name="Nom_Provincia">ATACAMA</Field><Field name="Tipo_Oficina">P</Field><Field name="Numero_BancoFacil">1</Field><Field name="Tipo_Cajero"/><Field name="Telefono_Asociado"/></MODULE_RESULT><MODULE_RESULT><Field name="Codigo">4</Field><Field name="Localidad">San Felipe</Field><Field name="Cod_Oficina">4</Field><Field name="Direccion">Calle Arturo Prat 83</Field><Field name="Codigo_postal"/><Field name="Telefono">34-2491477</Field><Field name="Desplazado"/><Field name="Nombre_Oficina">San Felipe</Field><Field name="Latitud">-32.7509124</Field><Field name="Longitud">-70.7216494</Field><Field name="Distancia">1427,7607076782</Field><Field name="Numero_Cajeros">2</Field><Field name="Horario"/><Field name="Nom_Provincia">VALPARAISO</Field><Field name="Tipo_Oficina">P</Field><Field name="Numero_BancoFacil">1</Field><Field name="Tipo_Cajero"/><Field name="Telefono_Asociado"/></MODULE_RESULT><MODULE_RESULT><Field name="Codigo">63</Field><Field name="Localidad">Los Andes</Field><Field name="Cod_Oficina">63</Field><Field name="Direccion">O'Higgins 358</Field><Field name="Codigo_postal"/><Field name="Telefono">34-2406174 - 34-2406882</Field><Field name="Desplazado"/><Field name="Nombre_Oficina">Los Andes</Field><Field name="Latitud">-32.8343091</Field><Field name="Longitud">-70.5984861</Field><Field name="Distancia">1435,8038454414</Field><Field name="Numero_Cajeros">2</Field><Field name="Horario"/><Field name="Nom_Provincia">VALPARAISO</Field><Field name="Tipo_Oficina">P</Field><Field name="Numero_BancoFacil">1</Field><Field name="Tipo_Cajero"/><Field name="Telefono_Asociado"/></MODULE_RESULT><MODULE_RESULT><Field name="Codigo">331</Field><Field name="Localidad">Colina</Field><Field name="Cod_Oficina">331</Field><Field name="Direccion">Avenida Colina Sur 14600</Field><Field name="Codigo_postal"/><Field name="Telefono">2 26638900</Field><Field name="Desplazado"/><Field name="Nombre_Oficina">Chicureo</Field><Field name="Latitud">-33.1932007</Field><Field name="Longitud">-70.6700269</Field><Field name="Distancia">1471,8399634051</Field><Field name="Numero_Cajeros">4</Field><Field name="Horario"/><Field name="Nom_Provincia">REGIÓN METROPOLITANA</Field><Field name="Tipo_Oficina">P</Field><Field name="Numero_BancoFacil">2</Field><Field name="Tipo_Cajero"/><Field name="Telefono_Asociado"/></MODULE_RESULT><MODULE_RESULT><Field name="Codigo">140</Field><Field name="Localidad">Lo Barnechea</Field><Field name="Cod_Oficina">140</Field><Field name="Direccion">Camino los Trapenses 3023</Field><Field name="Codigo_postal"/><Field name="Telefono">2 26792510</Field><Field name="Desplazado"/><Field name="Nombre_Oficina">Los Trapenses</Field><Field name="Latitud">-33.3476455</Field><Field name="Longitud">-70.5422286</Field><Field name="Distancia">1487,0326493686</Field><Field name="Numero_Cajeros">2</Field><Field name="Horario"/><Field name="Nom_Provincia">REGIÓN METROPOLITANA</Field><Field name="Tipo_Oficina">P</Field><Field name="Numero_BancoFacil">1</Field><Field name="Tipo_Cajero"/><Field name="Telefono_Asociado"/></MODULE_RESULT><MODULE_RESULT><Field name="Codigo">170</Field><Field name="Localidad">Quilicura</Field><Field name="Cod_Oficina">170</Field><Field name="Direccion">Av Bernardo O'Higgins 581</Field><Field name="Codigo_postal"/><Field name="Telefono">2 26791931</Field><Field name="Desplazado"/><Field name="Nombre_Oficina">Quilicura</Field><Field name="Latitud">-33.3487957</Field><Field name="Longitud">-70.7289714</Field><Field name="Distancia">1487,5461613957</Field><Field name="Numero_Cajeros">1</Field><Field name="Horario"/><Field name="Nom_Provincia">REGIÓN METROPOLITANA</Field><Field name="Tipo_Oficina">P</Field><Field name="Numero_BancoFacil">0</Field><Field name="Tipo_Cajero"/><Field name="Telefono_Asociado"/></MODULE_RESULT><MODULE_RESULT><Field name="Codigo">134</Field><Field name="Localidad">Lo Barnechea</Field><Field name="Cod_Oficina">134</Field><Field name="Direccion">Avenida La Dehesa 457</Field><Field name="Codigo_postal"/><Field name="Telefono">2 26791649</Field><Field name="Desplazado"/><Field name="Nombre_Oficina">La Dehesa</Field><Field name="Latitud">-33.3628891</Field><Field name="Longitud">-70.5149428</Field><Field name="Distancia">1488,5182721933</Field><Field name="Numero_Cajeros">2</Field><Field name="Horario"/><Field name="Nom_Provincia">REGIÓN METROPOLITANA</Field><Field name="Tipo_Oficina">P</Field><Field name="Numero_BancoFacil">1</Field><Field name="Tipo_Cajero"/><Field name="Telefono_Asociado"/></MODULE_RESULT><MODULE_RESULT><Field name="Codigo">29</Field><Field name="Localidad">Conchalí</Field><Field name="Cod_Oficina">29</Field><Field name="Direccion">Av. Américo Vespucio 2930</Field><Field name="Codigo_postal"/><Field name="Telefono">2 25135104</Field><Field name="Desplazado"/><Field name="Nombre_Oficina">Panamericana</Field><Field name="Latitud">-33.365642</Field><Field name="Longitud">-70.694405</Field><Field name="Distancia">1489,1388154782</Field><Field name="Numero_Cajeros">2</Field><Field name="Horario"/><Field name="Nom_Provincia">REGIÓN METROPOLITANA</Field><Field name="Tipo_Oficina">P</Field><Field name="Numero_BancoFacil">1</Field><Field name="Tipo_Cajero"/><Field name="Telefono_Asociado"/></MODULE_RESULT><MODULE_RESULT><Field name="Codigo">472</Field><Field name="Localidad">Huechuraba</Field><Field name="Cod_Oficina">472</Field><Field name="Direccion">Avenida Américo Vespucio 1737</Field><Field name="Codigo_postal"/><Field name="Telefono">2 26638528</Field><Field name="Desplazado"/><Field name="Nombre_Oficina">Mall Plaza Norte</Field><Field name="Latitud">-33.3662202</Field><Field name="Longitud">-70.6785295</Field><Field name="Distancia">1489,1573579389</Field><Field name="Numero_Cajeros">2</Field><Field name="Horario"/><Field name="Nom_Provincia">REGIÓN METROPOLITANA</Field><Field name="Tipo_Oficina">P</Field><Field name="Numero_BancoFacil">1</Field><Field name="Tipo_Cajero"/><Field name="Telefono_Asociado"/></MODULE_RESULT><MODULE_RESULT><Field name="Codigo">40</Field><Field name="Localidad">Las Condes</Field><Field name="Cod_Oficina">40</Field><Field name="Direccion">Avenida Las Condes 12207</Field><Field name="Codigo_postal"/><Field name="Telefono">2 26791638</Field><Field name="Desplazado"/><Field name="Nombre_Oficina">Cantagallo</Field><Field name="Latitud">-33.3733652</Field><Field name="Longitud">-70.5189365</Field><Field name="Distancia">1489,5711190904</Field><Field name="Numero_Cajeros">2</Field><Field name="Horario"/><Field name="Nom_Provincia">REGIÓN METROPOLITANA</Field><Field name="Tipo_Oficina">P</Field><Field name="Numero_BancoFacil">1</Field><Field name="Tipo_Cajero"/><Field name="Telefono_Asociado"/></MODULE_RESULT><MODULE_RESULT><Field name="Codigo">6</Field><Field name="Localidad">Vitacura</Field><Field name="Cod_Oficina">6</Field><Field name="Direccion">Santa María de Manquehue 6902</Field><Field name="Codigo_postal"/><Field name="Telefono">2 26791693</Field><Field name="Desplazado"/><Field name="Nombre_Oficina">Santa María de Manquehue</Field><Field name="Latitud">-33.3769508</Field><Field name="Longitud">-70.5694364</Field><Field name="Distancia">1490,0062396064</Field><Field name="Numero_Cajeros">2</Field><Field name="Horario"/><Field name="Nom_Provincia">REGIÓN METROPOLITANA</Field><Field name="Tipo_Oficina">P</Field><Field name="Numero_BancoFacil">1</Field><Field name="Tipo_Cajero"/><Field name="Telefono_Asociado"/></MODULE_RESULT><MODULE_RESULT><Field name="Codigo">233</Field><Field name="Localidad">Las Condes</Field><Field name="Cod_Oficina">233</Field><Field name="Direccion">Avenida Estoril 200</Field><Field name="Codigo_postal"/><Field name="Telefono">2 26638943</Field><Field name="Desplazado"/><Field name="Nombre_Oficina">Estoril Premium</Field><Field name="Latitud">-33.3845716</Field><Field name="Longitud">-70.5328756</Field><Field name="Distancia">1490,7110790582</Field><Field name="Numero_Cajeros">2</Field><Field name="Horario"/><Field name="Nom_Provincia">REGIÓN METROPOLITANA</Field><Field name="Tipo_Oficina">P</Field><Field name="Numero_BancoFacil">1</Field><Field name="Tipo_Cajero"/><Field name="Telefono_Asociado"/></MODULE_RESULT><MODULE_RESULT><Field name="Codigo">119</Field><Field name="Localidad">Vitacura</Field><Field name="Cod_Oficina">119</Field><Field name="Direccion">Avenida Padre Hurtado 1389</Field><Field name="Codigo_postal"/><Field name="Telefono">2 26791900</Field><Field name="Desplazado"/><Field name="Nombre_Oficina">Padre Hurtado</Field><Field name="Latitud">-33.3854446</Field><Field name="Longitud">-70.5502395</Field><Field name="Distancia">1490,8243846931</Field><Field name="Numero_Cajeros">2</Field><Field name="Horario"/><Field name="Nom_Provincia">REGIÓN METROPOLITANA</Field><Field name="Tipo_Oficina">P</Field><Field name="Numero_BancoFacil">1</Field><Field name="Tipo_Cajero"/><Field name="Telefono_Asociado"/></MODULE_RESULT><MODULE_RESULT><Field name="Codigo">473</Field><Field name="Localidad">Huechuraba</Field><Field name="Cod_Oficina">473</Field><Field name="Direccion">Santa Clara 301</Field><Field name="Codigo_postal"/><Field name="Telefono">2 26638456</Field><Field name="Desplazado"/><Field name="Nombre_Oficina">Ciudad Empresarial</Field><Field name="Latitud">-33.3875187</Field><Field name="Longitud">-70.6201758</Field><Field name="Distancia">1491,1570016809</Field><Field name="Numero_Cajeros">2</Field><Field name="Horario"/><Field name="Nom_Provincia">REGIÓN METROPOLITANA</Field><Field name="Tipo_Oficina">P</Field><Field name="Numero_BancoFacil">1</Field><Field name="Tipo_Cajero"/><Field name="Telefono_Asociado"/></MODULE_RESULT><MODULE_RESULT><Field name="Codigo">61</Field><Field name="Localidad">Vitacura</Field><Field name="Cod_Oficina">61</Field><Field name="Direccion">Vitacura 6471</Field><Field name="Codigo_postal"/><Field name="Telefono">2 26791654</Field><Field name="Desplazado"/><Field name="Nombre_Oficina">Los Cobres</Field><Field name="Latitud">-33.3893367</Field><Field name="Longitud">-70.5689811</Field><Field name="Distancia">1491,2438873162</Field><Field name="Numero_Cajeros">2</Field><Field name="Horario"/><Field name="Nom_Provincia">REGIÓN METROPOLITANA</Field><Field name="Tipo_Oficina">P</Field><Field name="Numero_BancoFacil">1</Field><Field name="Tipo_Cajero"/><Field name="Telefono_Asociado"/></MODULE_RESULT><MODULE_RESULT><Field name="Codigo">304</Field><Field name="Localidad">Viatacura</Field><Field name="Cod_Oficina">304</Field><Field name="Direccion">Av. Nueva Costanera 3979</Field><Field name="Codigo_postal"/><Field name="Telefono">2 26638828</Field><Field name="Desplazado"/><Field name="Nombre_Oficina">Nueva Costanera Premium</Field><Field name="Latitud">-33.3975315</Field><Field name="Longitud">-70.5973899</Field><Field name="Distancia">1492,113703086</Field><Field name="Numero_Cajeros">2</Field><Field name="Horario"/><Field name="Nom_Provincia">REGIÓN METROPOLITANA</Field><Field name="Tipo_Oficina">P</Field><Field name="Numero_BancoFacil">1</Field><Field name="Tipo_Cajero"/><Field name="Telefono_Asociado"/></MODULE_RESULT><MODULE_RESULT><Field name="Codigo">168</Field><Field name="Localidad">Las Condes</Field><Field name="Cod_Oficina">168</Field><Field name="Direccion">Camino El Alba 11969</Field><Field name="Codigo_postal"/><Field name="Telefono">2 26792657</Field><Field name="Desplazado"/><Field name="Nombre_Oficina">Mall Paseo Los Dominicos</Field><Field name="Latitud">-33.4010377</Field><Field name="Longitud">-70.5152247</Field><Field name="Distancia">1492,3331717215</Field><Field name="Numero_Cajeros">2</Field><Field name="Horario"/><Field name="Nom_Provincia">REGIÓN METROPOLITANA</Field><Field name="Tipo_Oficina">P</Field><Field name="Numero_BancoFacil">1</Field><Field name="Tipo_Cajero"/><Field name="Telefono_Asociado"/></MODULE_RESULT><MODULE_RESULT><Field name="Codigo">25</Field><Field name="Localidad">Vitacura</Field><Field name="Cod_Oficina">25</Field><Field name="Direccion">Avenida Vitacura 3790</Field><Field name="Codigo_postal"/><Field name="Telefono">2 26638539</Field><Field name="Desplazado"/><Field name="Nombre_Oficina">Lo Castillo</Field><Field name="Latitud">-33.4013714</Field><Field name="Longitud">-70.5935476</Field><Field name="Distancia">1492,4904879186</Field><Field name="Numero_Cajeros">2</Field><Field name="Horario"/><Field name="Nom_Provincia">REGIÓN METROPOLITANA</Field><Field name="Tipo_Oficina">P</Field><Field name="Numero_BancoFacil">1</Field><Field name="Tipo_Cajero"/><Field name="Telefono_Asociado"/></MODULE_RESULT><MODULE_RESULT><Field name="Codigo">17</Field><Field name="Localidad">Las Condes</Field><Field name="Cod_Oficina">17</Field><Field name="Direccion">Avenida Kennedy 5413</Field><Field name="Codigo_postal"/><Field name="Telefono">2 26638368</Field><Field name="Desplazado"/><Field name="Nombre_Oficina">Parque Arauco</Field><Field name="Latitud">-33.4019547</Field><Field name="Longitud">-70.5796966</Field><Field name="Distancia">1492,5238982641</Field><Field name="Numero_Cajeros">2</Field><Field name="Horario"/><Field name="Nom_Provincia">REGIÓN METROPOLITANA</Field><Field name="Tipo_Oficina">P</Field><Field name="Numero_BancoFacil">1</Field><Field name="Tipo_Cajero"/><Field name="Telefono_Asociado"/></MODULE_RESULT><MODULE_RESULT><Field name="Codigo">106</Field><Field name="Localidad">Las Condes</Field><Field name="Cod_Oficina">106</Field><Field name="Direccion">Avenida Presidente Riesco 5435</Field><Field name="Codigo_postal"/><Field name="Telefono">2 26638486</Field><Field name="Desplazado"/><Field name="Nombre_Oficina">Nueva Las Condes</Field><Field name="Latitud">-33.4049798</Field><Field name="Longitud">-70.575535</Field><Field name="Distancia">1492,8191301008</Field><Field name="Numero_Cajeros">2</Field><Field name="Horario"/><Field name="Nom_Provincia">REGIÓN METROPOLITANA</Field><Field name="Tipo_Oficina">P</Field><Field name="Numero_BancoFacil">1</Field><Field name="Tipo_Cajero"/><Field name="Telefono_Asociado"/></MODULE_RESULT><MODULE_RESULT><Field name="Codigo">115</Field><Field name="Localidad">Las Condes</Field><Field name="Cod_Oficina">115</Field><Field name="Direccion">Avenida Apoquindo 8375</Field><Field name="Codigo_postal"/><Field name="Telefono">2 26791604</Field><Field name="Desplazado"/><Field name="Nombre_Oficina">Los Dominicos</Field><Field name="Latitud">-33.4079283</Field><Field name="Longitud">-70.5458426</Field><Field name="Distancia">1493,0657143278</Field><Field name="Numero_Cajeros">2</Field><Field name="Horario"/><Field name="Nom_Provincia">REGIÓN METROPOLITANA</Field><Field name="Tipo_Oficina">P</Field><Field name="Numero_BancoFacil">1</Field><Field name="Tipo_Cajero"/><Field name="Telefono_Asociado"/></MODULE_RESULT><MODULE_RESULT><Field name="Codigo">24</Field><Field name="Localidad">Las Condes</Field><Field name="Cod_Oficina">24</Field><Field name="Direccion">Avenida Apoquindo 5680</Field><Field name="Codigo_postal"/><Field name="Telefono">2 26638334</Field><Field name="Desplazado"/><Field name="Nombre_Oficina">El Faro</Field><Field name="Latitud">-33.40969</Field><Field name="Longitud">-70.570747</Field><Field name="Distancia">1493,2819059405</Field><Field name="Numero_Cajeros">2</Field><Field name="Horario"/><Field name="Nom_Provincia">REGIÓN METROPOLITANA</Field><Field name="Tipo_Oficina">P</Field><Field name="Numero_BancoFacil">1</Field><Field name="Tipo_Cajero"/><Field name="Telefono_Asociado"/></MODULE_RESULT><MODULE_RESULT><Field name="Codigo">213</Field><Field name="Localidad">Las Condes</Field><Field name="Cod_Oficina">213</Field><Field name="Direccion">Avenida Apoquindo 4501</Field><Field name="Codigo_postal"/><Field name="Telefono">2 26792606</Field><Field name="Desplazado"/><Field name="Nombre_Oficina">Escuela Militar</Field><Field name="Latitud">-33.4137976</Field><Field name="Longitud">-70.5831794</Field><Field name="Distancia">1493,7141443203</Field><Field name="Numero_Cajeros">2</Field><Field name="Horario"/><Field name="Nom_Provincia">REGIÓN METROPOLITANA</Field><Field name="Tipo_Oficina">P</Field><Field name="Numero_BancoFacil">1</Field><Field name="Tipo_Cajero"/><Field name="Telefono_Asociado"/></MODULE_RESULT><MODULE_RESULT><Field name="Codigo">116</Field><Field name="Localidad">Las Condes</Field><Field name="Cod_Oficina">116</Field><Field name="Direccion">Isidora Goyenechea 2880</Field><Field name="Codigo_postal"/><Field name="Telefono">2 26791923</Field><Field name="Desplazado"/><Field name="Nombre_Oficina">Isidora Goyenechea</Field><Field name="Latitud">-33.4137419</Field><Field name="Longitud">-70.6025921</Field><Field name="Distancia">1493,7442733405</Field><Field name="Numero_Cajeros">2</Field><Field name="Horario"/><Field name="Nom_Provincia">REGIÓN METROPOLITANA</Field><Field name="Tipo_Oficina">P</Field><Field name="Numero_BancoFacil">1</Field><Field name="Tipo_Cajero"/><Field name="Telefono_Asociado"/></MODULE_RESULT><MODULE_RESULT><Field name="Codigo">319</Field><Field name="Localidad">Las Condes</Field><Field name="Cod_Oficina">319</Field><Field name="Direccion">Av Costanera Sur 2710</Field><Field name="Codigo_postal"/><Field name="Telefono">2 26638921</Field><Field name="Desplazado"/><Field name="Nombre_Oficina">Parque Titanium</Field><Field name="Latitud">-33.4143449</Field><Field name="Longitud">-70.6062666</Field><Field name="Distancia">1493,8116030566</Field><Field name="Numero_Cajeros">2</Field><Field name="Horario"/><Field name="Nom_Provincia">REGIÓN METROPOLITANA</Field><Field name="Tipo_Oficina">P</Field><Field name="Numero_BancoFacil">1</Field><Field name="Tipo_Cajero"/><Field name="Telefono_Asociado"/></MODULE_RESULT><MODULE_RESULT><Field name="Codigo">317</Field><Field name="Localidad">Las Condes</Field><Field name="Cod_Oficina">317</Field><Field name="Direccion">Avenida Vitacura 2736</Field><Field name="Codigo_postal"/><Field name="Telefono">2 26638930</Field><Field name="Desplazado"/><Field name="Nombre_Oficina">World Trade Center</Field><Field name="Latitud">-33.4156319</Field><Field name="Longitud">-70.6043444</Field><Field name="Distancia">1493,9365850814</Field><Field name="Numero_Cajeros">2</Field><Field name="Horario"/><Field name="Nom_Provincia">REGIÓN METROPOLITANA</Field><Field name="Tipo_Oficina">P</Field><Field name="Numero_BancoFacil">1</Field><Field name="Tipo_Cajero"/><Field name="Telefono_Asociado"/></MODULE_RESULT><MODULE_RESULT><Field name="Codigo">111</Field><Field name="Localidad">Las Condes</Field><Field name="Cod_Oficina">111</Field><Field name="Direccion">Avenida Apoquindo 3640</Field><Field name="Codigo_postal"/><Field name="Telefono">2 26791619</Field><Field name="Desplazado"/><Field name="Nombre_Oficina">El Golf Premium</Field><Field name="Latitud">-33.4159875</Field><Field name="Longitud">-70.5926733</Field><Field name="Distancia">1493,9502405802</Field><Field name="Numero_Cajeros">4</Field><Field name="Horario"/><Field name="Nom_Provincia">REGIÓN METROPOLITANA</Field><Field name="Tipo_Oficina">P</Field><Field name="Numero_BancoFacil">2</Field><Field name="Tipo_Cajero"/><Field name="Telefono_Asociado"/></MODULE_RESULT><MODULE_RESULT><Field name="Codigo">37</Field><Field name="Localidad">Las Condes</Field><Field name="Cod_Oficina">37</Field><Field name="Direccion">Avenida Cuarto Centenario 7393</Field><Field name="Codigo_postal"/><Field name="Telefono">2 26638855</Field><Field name="Desplazado"/><Field name="Nombre_Oficina">Tomás Moro</Field><Field name="Latitud">-33.4171756</Field><Field name="Longitud">-70.5538469</Field><Field name="Distancia">1494,002747426</Field><Field name="Numero_Cajeros">2</Field><Field name="Horario"/><Field name="Nom_Provincia">REGIÓN METROPOLITANA</Field><Field name="Tipo_Oficina">P</Field><Field name="Numero_BancoFacil">1</Field><Field name="Tipo_Cajero"/><Field name="Telefono_Asociado"/></MODULE_RESULT><MODULE_RESULT><Field name="Codigo">336</Field><Field name="Localidad">Las Condes</Field><Field name="Cod_Oficina">336</Field><Field name="Direccion">Avenida Apoquindo 2827</Field><Field name="Codigo_postal"/><Field name="Telefono">2 25135158</Field><Field name="Desplazado"/><Field name="Nombre_Oficina">Territoria</Field><Field name="Latitud">-33.4177257</Field><Field name="Longitud">-70.6000939</Field><Field name="Distancia">1494,1378470633</Field><Field name="Numero_Cajeros">4</Field><Field name="Horario"/><Field name="Nom_Provincia">REGIÓN METROPOLITANA</Field><Field name="Tipo_Oficina">P</Field><Field name="Numero_BancoFacil">2</Field><Field name="Tipo_Cajero"/><Field name="Telefono_Asociado"/></MODULE_RESULT><MODULE_RESULT><Field name="Codigo">321</Field><Field name="Localidad">Providencia</Field><Field name="Cod_Oficina">321</Field><Field name="Direccion">Avenida 11 de septiembre 2606</Field><Field name="Codigo_postal"/><Field name="Telefono">2 26638951</Field><Field name="Desplazado"/><Field name="Nombre_Oficina">Metro Tobalaba</Field><Field name="Latitud">-33.4177214</Field><Field name="Longitud">-70.6030574</Field><Field name="Distancia">1494,1430375873</Field><Field name="Numero_Cajeros">0</Field><Field name="Horario"/><Field name="Nom_Provincia">REGIÓN METROPOLITANA</Field><Field name="Tipo_Oficina">P</Field><Field name="Numero_BancoFacil">0</Field><Field name="Tipo_Cajero"/><Field name="Telefono_Asociado"/></MODULE_RESULT><MODULE_RESULT><Field name="Codigo">394</Field><Field name="Localidad">Providencia</Field><Field name="Cod_Oficina">394</Field><Field name="Direccion">Av. Andrés Bello 2465</Field><Field name="Codigo_postal"/><Field name="Telefono">2 26638570</Field><Field name="Desplazado"/><Field name="Nombre_Oficina">Costanera Center</Field><Field name="Latitud">-33.4177376</Field><Field name="Longitud">-70.607335</Field><Field name="Distancia">1494,1528736126</Field><Field name="Numero_Cajeros">2</Field><Field name="Horario"/><Field name="Nom_Provincia">REGIÓN METROPOLITANA</Field><Field name="Tipo_Oficina">P</Field><Field name="Numero_BancoFacil">1</Field><Field name="Tipo_Cajero"/><Field name="Telefono_Asociado"/></MODULE_RESULT><MODULE_RESULT><Field name="Codigo">1</Field><Field name="Localidad">Providencia</Field><Field name="Cod_Oficina">1</Field><Field name="Direccion">Ricardo Lyon 77</Field><Field name="Codigo_postal"/><Field name="Telefono">2 26792943</Field><Field name="Desplazado"/><Field name="Nombre_Oficina">Lyon</Field><Field name="Latitud">-33.4226384</Field><Field name="Longitud">-70.6094717</Field><Field name="Distancia">1494,6470104896</Field><Field name="Numero_Cajeros">3</Field><Field name="Horario"/><Field name="Nom_Provincia">REGIÓN METROPOLITANA</Field><Field name="Tipo_Oficina">P</Field><Field name="Numero_BancoFacil">2</Field><Field name="Tipo_Cajero"/><Field name="Telefono_Asociado"/></MODULE_RESULT><MODULE_RESULT><Field name="Codigo">36</Field><Field name="Localidad">Providencia</Field><Field name="Cod_Oficina">36</Field><Field name="Direccion">Avenida 11 Septiembre 2045</Field><Field name="Codigo_postal"/><Field name="Telefono">26792358</Field><Field name="Desplazado"/><Field name="Nombre_Oficina">Providencia</Field><Field name="Latitud">-33.424267</Field><Field name="Longitud">-70.611566</Field><Field name="Distancia">1494,8139350397</Field><Field name="Numero_Cajeros">4</Field><Field name="Horario"/><Field name="Nom_Provincia">REGIÓN METROPOLITANA</Field><Field name="Tipo_Oficina">P</Field><Field name="Numero_BancoFacil">2</Field><Field name="Tipo_Cajero"/><Field name="Telefono_Asociado"/></MODULE_RESULT><MODULE_RESULT><Field name="Codigo">328</Field><Field name="Localidad">Providencia</Field><Field name="Cod_Oficina">328</Field><Field name="Direccion">La Concepción 46</Field><Field name="Codigo_postal"/><Field name="Telefono">26638890</Field><Field name="Desplazado"/><Field name="Nombre_Oficina">Providencia Premium</Field><Field name="Latitud">-33.4254163</Field><Field name="Longitud">-70.6151943</Field><Field name="Distancia">1494,9360070416</Field><Field name="Numero_Cajeros">2</Field><Field name="Horario"/><Field name="Nom_Provincia">REGIÓN METROPOLITANA</Field><Field name="Tipo_Oficina">P</Field><Field name="Numero_BancoFacil">1</Field><Field name="Tipo_Cajero"/><Field name="Telefono_Asociado"/></MODULE_RESULT><MODULE_RESULT><Field name="Codigo">381</Field><Field name="Localidad">Recoleta</Field><Field name="Cod_Oficina">381</Field><Field name="Direccion">Avenida Recoleta 442</Field><Field name="Codigo_postal"/><Field name="Telefono">2 26638990</Field><Field name="Desplazado"/><Field name="Nombre_Oficina">Recoleta Dominica</Field><Field name="Latitud">-33.4278043</Field><Field name="Longitud">-70.6467615</Field><Field name="Distancia">1495,2407936537</Field><Field name="Numero_Cajeros">2</Field><Field name="Horario"/><Field name="Nom_Provincia">REGIÓN METROPOLITANA</Field><Field name="Tipo_Oficina">P</Field><Field name="Numero_BancoFacil">1</Field><Field name="Tipo_Cajero"/><Field name="Telefono_Asociado"/></MODULE_RESULT><MODULE_RESULT><Field name="Codigo">478</Field><Field name="Localidad">Recoleta</Field><Field name="Cod_Oficina">478</Field><Field name="Direccion">Avenida Recoleta 442</Field><Field name="Codigo_postal"/><Field name="Telefono">2 26638991</Field><Field name="Desplazado"/><Field name="Nombre_Oficina">Recoleta Dominica Premium</Field><Field name="Latitud">-33.4278043</Field><Field name="Longitud">-70.6467615</Field><Field name="Distancia">1495,2407936537</Field><Field name="Numero_Cajeros">0</Field><Field name="Horario"/><Field name="Nom_Provincia">REGIÓN METROPOLITANA</Field><Field name="Tipo_Oficina">P</Field><Field name="Numero_BancoFacil">0</Field><Field name="Tipo_Cajero"/><Field name="Telefono_Asociado"/></MODULE_RESULT><MODULE_RESULT><Field name="Codigo">84</Field><Field name="Localidad">Providencia</Field><Field name="Cod_Oficina">84</Field><Field name="Direccion">Providencia 1082</Field><Field name="Codigo_postal"/><Field name="Telefono">2 26638688</Field><Field name="Desplazado"/><Field name="Nombre_Oficina">Tajamar</Field><Field name="Latitud">-33.4301022</Field><Field name="Longitud">-70.6224584</Field><Field name="Distancia">1495,4191076262</Field><Field name="Numero_Cajeros">2</Field><Field name="Horario"/><Field name="Nom_Provincia">REGIÓN METROPOLITANA</Field><Field name="Tipo_Oficina">P</Field><Field name="Numero_BancoFacil">1</Field><Field name="Tipo_Cajero"/><Field name="Telefono_Asociado"/></MODULE_RESULT><MODULE_RESULT><Field name="Codigo">117</Field><Field name="Localidad">Las Condes</Field><Field name="Cod_Oficina">117</Field><Field name="Direccion">Bilbao 4038</Field><Field name="Codigo_postal"/><Field name="Telefono">2 26791911</Field><Field name="Desplazado"/><Field name="Nombre_Oficina">Bilbao</Field><Field name="Latitud">-33.4312737</Field><Field name="Longitud">-70.5804069</Field><Field name="Distancia">1495,4565928343</Field><Field name="Numero_Cajeros">2</Field><Field name="Horario"/><Field name="Nom_Provincia">REGIÓN METROPOLITANA</Field><Field name="Tipo_Oficina">P</Field><Field name="Numero_BancoFacil">1</Field><Field name="Tipo_Cajero"/><Field name="Telefono_Asociado"/></MODULE_RESULT><MODULE_RESULT><Field name="Codigo">32</Field><Field name="Localidad">Santiago</Field><Field name="Cod_Oficina">32</Field><Field name="Direccion">San Antonio 735</Field><Field name="Codigo_postal"/><Field name="Telefono">26638145</Field><Field name="Desplazado"/><Field name="Nombre_Oficina">Parque Forestal</Field><Field name="Latitud">-33.4347011</Field><Field name="Longitud">-70.6488067</Field><Field name="Distancia">1495,9348131496</Field><Field name="Numero_Cajeros">2</Field><Field name="Horario"/><Field name="Nom_Provincia">REGIÓN METROPOLITANA</Field><Field name="Tipo_Oficina">P</Field><Field name="Numero_BancoFacil">1</Field><Field name="Tipo_Cajero"/><Field name="Telefono_Asociado"/></MODULE_RESULT><MODULE_RESULT><Field name="Codigo">59</Field><Field name="Localidad">Santiago</Field><Field name="Cod_Oficina">59</Field><Field name="Direccion">San Pablo 3190</Field><Field name="Codigo_postal"/><Field name="Telefono">2 26791668</Field><Field name="Desplazado"/><Field name="Nombre_Oficina">San Pablo</Field><Field name="Latitud">-33.4358031</Field><Field name="Longitud">-70.6790657</Field><Field name="Distancia">1496,114912505</Field><Field name="Numero_Cajeros">2</Field><Field name="Horario"/><Field name="Nom_Provincia">REGIÓN METROPOLITANA</Field><Field name="Tipo_Oficina">P</Field><Field name="Numero_BancoFacil">1</Field><Field name="Tipo_Cajero"/><Field name="Telefono_Asociado"/></MODULE_RESULT><MODULE_RESULT><Field name="Codigo">68</Field><Field name="Localidad">Providencia</Field><Field name="Cod_Oficina">68</Field><Field name="Direccion">Avenida Pedro de Valdivia 1718</Field><Field name="Codigo_postal"/><Field name="Telefono">2 26638674</Field><Field name="Desplazado"/><Field name="Nombre_Oficina">Plaza Pedro de Valdivia</Field><Field name="Latitud">-33.4383646</Field><Field name="Longitud">-70.6073974</Field><Field name="Distancia">1496,2153085094</Field><Field name="Numero_Cajeros">2</Field><Field name="Horario"/><Field name="Nom_Provincia">REGIÓN METROPOLITANA</Field><Field name="Tipo_Oficina">P</Field><Field name="Numero_BancoFacil">1</Field><Field name="Tipo_Cajero"/><Field name="Telefono_Asociado"/></MODULE_RESULT><MODULE_RESULT><Field name="Codigo">74</Field><Field name="Localidad">Santiago</Field><Field name="Cod_Oficina">74</Field><Field name="Direccion">Avenida Libertador B.O'Higgins 108</Field><Field name="Codigo_postal"/><Field name="Telefono">2 26791661</Field><Field name="Desplazado"/><Field name="Nombre_Oficina">Plaza Italia</Field><Field name="Latitud">-33.437928</Field><Field name="Longitud">-70.637054</Field><Field name="Distancia">1496,2319177069</Field><Field name="Numero_Cajeros">2</Field><Field name="Horario"/><Field name="Nom_Provincia">REGIÓN METROPOLITANA</Field><Field name="Tipo_Oficina">P</Field><Field name="Numero_BancoFacil">1</Field><Field name="Tipo_Cajero"/><Field name="Telefono_Asociado"/></MODULE_RESULT><MODULE_RESULT><Field name="Codigo">90</Field><Field name="Localidad">La Reina</Field><Field name="Cod_Oficina">90</Field><Field name="Direccion">Aguas Claras 1655</Field><Field name="Codigo_postal"/><Field name="Telefono">2 26792670</Field><Field name="Desplazado"/><Field name="Nombre_Oficina">La Reina</Field><Field name="Latitud">-33.4395356</Field><Field name="Longitud">-70.5568892</Field><Field name="Distancia">1496,2432919514</Field><Field name="Numero_Cajeros">2</Field><Field name="Horario"/><Field name="Nom_Provincia">REGIÓN METROPOLITANA</Field><Field name="Tipo_Oficina">P</Field><Field name="Numero_BancoFacil">1</Field><Field name="Tipo_Cajero"/><Field name="Telefono_Asociado"/></MODULE_RESULT><MODULE_RESULT><Field name="Codigo">77</Field><Field name="Localidad">Santiago</Field><Field name="Cod_Oficina">77</Field><Field name="Direccion">Miraflores 399</Field><Field name="Codigo_postal"/><Field name="Telefono">2 26638617</Field><Field name="Desplazado"/><Field name="Nombre_Oficina">Miraflores</Field><Field name="Latitud">-33.4380367</Field><Field name="Longitud">-70.6454919</Field><Field name="Distancia">1496,2610042868</Field><Field name="Numero_Cajeros">2</Field><Field name="Horario"/><Field name="Nom_Provincia">REGIÓN METROPOLITANA</Field><Field name="Tipo_Oficina">P</Field><Field name="Numero_BancoFacil">1</Field><Field name="Tipo_Cajero"/><Field name="Telefono_Asociado"/></MODULE_RESULT><MODULE_RESULT><Field name="Codigo">451</Field><Field name="Localidad">Santiago</Field><Field name="Cod_Oficina">451</Field><Field name="Direccion">Huérfanos 676</Field><Field name="Codigo_postal"/><Field name="Telefono">2 26791823</Field><Field name="Desplazado"/><Field name="Nombre_Oficina">Santa Lucia</Field><Field name="Latitud">-33.439167</Field><Field name="Longitud">-70.64651</Field><Field name="Distancia">1496,3762375062</Field><Field name="Numero_Cajeros">0</Field><Field name="Horario"/><Field name="Nom_Provincia">REGIÓN METROPOLITANA</Field><Field name="Tipo_Oficina">P</Field><Field name="Numero_BancoFacil">0</Field><Field name="Tipo_Cajero"/><Field name="Telefono_Asociado"/></MODULE_RESULT><MODULE_RESULT><Field name="Codigo">395</Field><Field name="Localidad">Santiago</Field><Field name="Cod_Oficina">395</Field><Field name="Direccion">Estado 312</Field><Field name="Codigo_postal"/><Field name="Telefono">2 26638005</Field><Field name="Desplazado"/><Field name="Nombre_Oficina">Estado</Field><Field name="Latitud">-33.4393945</Field><Field name="Longitud">-70.6495676</Field><Field name="Distancia">1496,4057215592</Field><Field name="Numero_Cajeros">2</Field><Field name="Horario"/><Field name="Nom_Provincia">REGIÓN METROPOLITANA</Field><Field name="Tipo_Oficina">P</Field><Field name="Numero_BancoFacil">1</Field><Field name="Tipo_Cajero"/><Field name="Telefono_Asociado"/></MODULE_RESULT><MODULE_RESULT><Field name="Codigo">21</Field><Field name="Localidad">Santiago</Field><Field name="Cod_Oficina">21</Field><Field name="Direccion">Huérfanos 1090</Field><Field name="Codigo_postal"/><Field name="Telefono">2 26792041</Field><Field name="Desplazado"/><Field name="Nombre_Oficina">Bandera</Field><Field name="Latitud">-33.4397479</Field><Field name="Longitud">-70.6521155</Field><Field name="Distancia">1496,4467165123</Field><Field name="Numero_Cajeros">4</Field><Field name="Horario"/><Field name="Nom_Provincia">REGIÓN METROPOLITANA</Field><Field name="Tipo_Oficina">P</Field><Field name="Numero_BancoFacil">2</Field><Field name="Tipo_Cajero"/><Field name="Telefono_Asociado"/></MODULE_RESULT><MODULE_RESULT><Field name="Codigo">333</Field><Field name="Localidad">Santiago</Field><Field name="Cod_Oficina">333</Field><Field name="Direccion">Agustinas 690</Field><Field name="Codigo_postal"/><Field name="Telefono">26791443</Field><Field name="Desplazado"/><Field name="Nombre_Oficina">Teatro Municipal</Field><Field name="Latitud">-33.4403963</Field><Field name="Longitud">-70.6464733</Field><Field name="Distancia">1496,4990574087</Field><Field name="Numero_Cajeros">2</Field><Field name="Horario"/><Field name="Nom_Provincia">REGIÓN METROPOLITANA</Field><Field name="Tipo_Oficina">P</Field><Field name="Numero_BancoFacil">1</Field><Field name="Tipo_Cajero"/><Field name="Telefono_Asociado"/></MODULE_RESULT><MODULE_RESULT><Field name="Codigo">35</Field><Field name="Localidad">Santiago</Field><Field name="Cod_Oficina">35</Field><Field name="Direccion">Moneda 906</Field><Field name="Codigo_postal"/><Field name="Telefono">2 26638662</Field><Field name="Desplazado"/><Field name="Nombre_Oficina">Moneda</Field><Field name="Latitud">-33.4418025</Field><Field name="Longitud">-70.649309</Field><Field name="Distancia">1496,6458901938</Field><Field name="Numero_Cajeros">4</Field><Field name="Horario"/><Field name="Nom_Provincia">REGIÓN METROPOLITANA</Field><Field name="Tipo_Oficina">P</Field><Field name="Numero_BancoFacil">2</Field><Field name="Tipo_Cajero"/><Field name="Telefono_Asociado"/></MODULE_RESULT><MODULE_RESULT><Field name="Codigo">474</Field><Field name="Localidad">Santiago</Field><Field name="Cod_Oficina">474</Field><Field name="Direccion">Moneda 967</Field><Field name="Codigo_postal"/><Field name="Telefono">2 26638497</Field><Field name="Desplazado"/><Field name="Nombre_Oficina">Matias Cousiño</Field><Field name="Latitud">-33.441829</Field><Field name="Longitud">-70.6501598</Field><Field name="Distancia">1496,6504241988</Field><Field name="Numero_Cajeros">2</Field><Field name="Horario"/><Field name="Nom_Provincia">REGIÓN METROPOLITANA</Field><Field name="Tipo_Oficina">P</Field><Field name="Numero_BancoFacil">1</Field><Field name="Tipo_Cajero"/><Field name="Telefono_Asociado"/></MODULE_RESULT><MODULE_RESULT><Field name="Codigo">104</Field><Field name="Localidad">Santiago</Field><Field name="Cod_Oficina">104</Field><Field name="Direccion">Moneda 1096</Field><Field name="Codigo_postal"/><Field name="Telefono">2 26638415</Field><Field name="Desplazado"/><Field name="Nombre_Oficina">La Bolsa</Field><Field name="Latitud">-33.4420996</Field><Field name="Longitud">-70.6518198</Field><Field name="Distancia">1496,6811685493</Field><Field name="Numero_Cajeros">2</Field><Field name="Horario"/><Field name="Nom_Provincia">REGIÓN METROPOLITANA</Field><Field name="Tipo_Oficina">P</Field><Field name="Numero_BancoFacil">1</Field><Field name="Tipo_Cajero"/><Field name="Telefono_Asociado"/></MODULE_RESULT><MODULE_RESULT><Field name="Codigo">329</Field><Field name="Localidad">Santiago</Field><Field name="Cod_Oficina">329</Field><Field name="Direccion">Moneda 1096</Field><Field name="Codigo_postal"/><Field name="Telefono">2 26638876</Field><Field name="Desplazado"/><Field name="Nombre_Oficina">La Bolsa Premium</Field><Field name="Latitud">-33.4420996</Field><Field name="Longitud">-70.6518198</Field><Field name="Distancia">1496,6811685493</Field><Field name="Numero_Cajeros">0</Field><Field name="Horario"/><Field name="Nom_Provincia">REGIÓN METROPOLITANA</Field><Field name="Tipo_Oficina">P</Field><Field name="Numero_BancoFacil">0</Field><Field name="Tipo_Cajero"/><Field name="Telefono_Asociado"/></MODULE_RESULT><MODULE_RESULT><Field name="Codigo">28</Field><Field name="Localidad">Santiago</Field><Field name="Cod_Oficina">28</Field><Field name="Direccion">Avenida Libertador Bernardo O'Higgins 2682</Field><Field name="Codigo_postal"/><Field name="Telefono">2 22906607</Field><Field name="Desplazado"/><Field name="Nombre_Oficina">Alameda</Field><Field name="Latitud">-33.4495803</Field><Field name="Longitud">-70.6737135</Field><Field name="Distancia">1497,4794300368</Field><Field name="Numero_Cajeros">2</Field><Field name="Horario"/><Field name="Nom_Provincia">REGIÓN METROPOLITANA</Field><Field name="Tipo_Oficina">P</Field><Field name="Numero_BancoFacil">1</Field><Field name="Tipo_Cajero"/><Field name="Telefono_Asociado"/></MODULE_RESULT><MODULE_RESULT><Field name="Codigo">66</Field><Field name="Localidad">Ñuñoa</Field><Field name="Cod_Oficina">66</Field><Field name="Direccion">Avenida Irarrazaval 5442</Field><Field name="Codigo_postal"/><Field name="Telefono">2 26638592</Field><Field name="Desplazado"/><Field name="Nombre_Oficina">Plaza Egaña</Field><Field name="Latitud">-33.4532368</Field><Field name="Longitud">-70.5733848</Field><Field name="Distancia">1497,6404362513</Field><Field name="Numero_Cajeros">2</Field><Field name="Horario"/><Field name="Nom_Provincia">REGIÓN METROPOLITANA</Field><Field name="Tipo_Oficina">P</Field><Field name="Numero_BancoFacil">1</Field><Field name="Tipo_Cajero"/><Field name="Telefono_Asociado"/></MODULE_RESULT><MODULE_RESULT><Field name="Codigo">54</Field><Field name="Localidad">Santiago</Field><Field name="Cod_Oficina">54</Field><Field name="Direccion">San Diego 601</Field><Field name="Codigo_postal"/><Field name="Telefono">2 26638844</Field><Field name="Desplazado"/><Field name="Nombre_Oficina">San Diego</Field><Field name="Latitud">-33.4527892</Field><Field name="Longitud">-70.6501923</Field><Field name="Distancia">1497,7462468048</Field><Field name="Numero_Cajeros">2</Field><Field name="Horario"/><Field name="Nom_Provincia">REGIÓN METROPOLITANA</Field><Field name="Tipo_Oficina">P</Field><Field name="Numero_BancoFacil">1</Field><Field name="Tipo_Cajero"/><Field name="Telefono_Asociado"/></MODULE_RESULT><MODULE_RESULT><Field name="Codigo">79</Field><Field name="Localidad">Santiago</Field><Field name="Cod_Oficina">79</Field><Field name="Direccion">Vicuña Mackenna 888</Field><Field name="Codigo_postal"/><Field name="Telefono">26791683</Field><Field name="Desplazado"/><Field name="Nombre_Oficina">Vicuña Mackenna</Field><Field name="Latitud">-33.4532353</Field><Field name="Longitud">-70.6304153</Field><Field name="Distancia">1497,7483147392</Field><Field name="Numero_Cajeros">2</Field><Field name="Horario"/><Field name="Nom_Provincia">REGIÓN METROPOLITANA</Field><Field name="Tipo_Oficina">P</Field><Field name="Numero_BancoFacil">1</Field><Field name="Tipo_Cajero"/><Field name="Telefono_Asociado"/></MODULE_RESULT><MODULE_RESULT><Field name="Codigo">27</Field><Field name="Localidad">Ñuñoa</Field><Field name="Cod_Oficina">27</Field><Field name="Direccion">Irarrázaval 2711</Field><Field name="Codigo_postal"/><Field name="Telefono">2 26638518</Field><Field name="Desplazado"/><Field name="Nombre_Oficina">Ñuñoa</Field><Field name="Latitud">-33.4545437</Field><Field name="Longitud">-70.6028912</Field><Field name="Distancia">1497,8242840098</Field><Field name="Numero_Cajeros">2</Field><Field name="Horario"/><Field name="Nom_Provincia">REGIÓN METROPOLITANA</Field><Field name="Tipo_Oficina">P</Field><Field name="Numero_BancoFacil">1</Field><Field name="Tipo_Cajero"/><Field name="Telefono_Asociado"/></MODULE_RESULT><MODULE_RESULT><Field name="Codigo">325</Field><Field name="Localidad">Estación Central</Field><Field name="Cod_Oficina">325</Field><Field name="Direccion">Avenida Libertador Bernardo Ohiggins 3902</Field><Field name="Codigo_postal"/><Field name="Telefono">2 26638967</Field><Field name="Desplazado"/><Field name="Nombre_Oficina">Alameda General Velasquez</Field><Field name="Latitud">-33.4535598</Field><Field name="Longitud">-70.6889574</Field><Field name="Distancia">1497,9142234058</Field><Field name="Numero_Cajeros">2</Field><Field name="Horario"/><Field name="Nom_Provincia">REGIÓN METROPOLITANA</Field><Field name="Tipo_Oficina">P</Field><Field name="Numero_BancoFacil">1</Field><Field name="Tipo_Cajero"/><Field name="Telefono_Asociado"/></MODULE_RESULT><MODULE_RESULT><Field name="Codigo">67</Field><Field name="Localidad">Macul</Field><Field name="Cod_Oficina">67</Field><Field name="Direccion">José Pedro Alessandri 2400</Field><Field name="Codigo_postal"/><Field name="Telefono">2 26638834</Field><Field name="Desplazado"/><Field name="Nombre_Oficina">Rodrigo de Araya</Field><Field name="Latitud">-33.4641136</Field><Field name="Longitud">-70.5982575</Field><Field name="Distancia">1498,7723713105</Field><Field name="Numero_Cajeros">2</Field><Field name="Horario"/><Field name="Nom_Provincia">REGIÓN METROPOLITANA</Field><Field name="Tipo_Oficina">P</Field><Field name="Numero_BancoFacil">1</Field><Field name="Tipo_Cajero"/><Field name="Telefono_Asociado"/></MODULE_RESULT><MODULE_RESULT><Field name="Codigo">82</Field><Field name="Localidad">San Joaquín</Field><Field name="Cod_Oficina">82</Field><Field name="Direccion">Santa Elena 2235</Field><Field name="Codigo_postal"/><Field name="Telefono">2 25447706</Field><Field name="Desplazado"/><Field name="Nombre_Oficina">Santa Elena</Field><Field name="Latitud">-33.4723785</Field><Field name="Longitud">-70.6264231</Field><Field name="Distancia">1499,6539611363</Field><Field name="Numero_Cajeros">2</Field><Field name="Horario"/><Field name="Nom_Provincia">REGIÓN METROPOLITANA</Field><Field name="Tipo_Oficina">P</Field><Field name="Numero_BancoFacil">1</Field><Field name="Tipo_Cajero"/><Field name="Telefono_Asociado"/></MODULE_RESULT><MODULE_RESULT><Field name="Codigo">85</Field><Field name="Localidad">Santiago</Field><Field name="Cod_Oficina">85</Field><Field name="Direccion">San Diego 2168</Field><Field name="Codigo_postal"/><Field name="Telefono">2 26638824</Field><Field name="Desplazado"/><Field name="Nombre_Oficina">Franklin</Field><Field name="Latitud">-33.4743923</Field><Field name="Longitud">-70.6481864</Field><Field name="Distancia">1499,901600346</Field><Field name="Numero_Cajeros">2</Field><Field name="Horario"/><Field name="Nom_Provincia">REGIÓN METROPOLITANA</Field><Field name="Tipo_Oficina">P</Field><Field name="Numero_BancoFacil">1</Field><Field name="Tipo_Cajero"/><Field name="Telefono_Asociado"/></MODULE_RESULT><MODULE_RESULT><Field name="Codigo">108</Field><Field name="Localidad">Peñalolen</Field><Field name="Cod_Oficina">108</Field><Field name="Direccion">Avenida Consistorial 2701</Field><Field name="Codigo_postal"/><Field name="Telefono">2 26638627</Field><Field name="Desplazado"/><Field name="Nombre_Oficina">Peñalolen</Field><Field name="Latitud">-33.4845717</Field><Field name="Longitud">-70.54755</Field><Field name="Distancia">1500,7317676163</Field><Field name="Numero_Cajeros">2</Field><Field name="Horario"/><Field name="Nom_Provincia">REGIÓN METROPOLITANA</Field><Field name="Tipo_Oficina">P</Field><Field name="Numero_BancoFacil">1</Field><Field name="Tipo_Cajero"/><Field name="Telefono_Asociado"/></MODULE_RESULT><MODULE_RESULT><Field name="Codigo">38</Field><Field name="Localidad">Cerrillos</Field><Field name="Cod_Oficina">38</Field><Field name="Direccion">Avenida Cerrillos 4030</Field><Field name="Codigo_postal"/><Field name="Telefono">2 26638697</Field><Field name="Desplazado"/><Field name="Nombre_Oficina">Lo Valledor</Field><Field name="Latitud">-33.4819635</Field><Field name="Longitud">-70.6858546</Field><Field name="Distancia">1500,7460916095</Field><Field name="Numero_Cajeros">2</Field><Field name="Horario"/><Field name="Nom_Provincia">REGIÓN METROPOLITANA</Field><Field name="Tipo_Oficina">P</Field><Field name="Numero_BancoFacil">1</Field><Field name="Tipo_Cajero"/><Field name="Telefono_Asociado"/></MODULE_RESULT><MODULE_RESULT><Field name="Codigo">78</Field><Field name="Localidad">San Miguel</Field><Field name="Cod_Oficina">78</Field><Field name="Direccion">El Llano Subercaseux 3259</Field><Field name="Codigo_postal"/><Field name="Telefono">2 26791645</Field><Field name="Desplazado"/><Field name="Nombre_Oficina">El Llano</Field><Field name="Latitud">-33.4839285</Field><Field name="Longitud">-70.6500745</Field><Field name="Distancia">1500,8591527925</Field><Field name="Numero_Cajeros">2</Field><Field name="Horario"/><Field name="Nom_Provincia">REGIÓN METROPOLITANA</Field><Field name="Tipo_Oficina">P</Field><Field name="Numero_BancoFacil">1</Field><Field name="Tipo_Cajero"/><Field name="Telefono_Asociado"/></MODULE_RESULT><MODULE_RESULT><Field name="Codigo">41</Field><Field name="Localidad">Maipú</Field><Field name="Cod_Oficina">41</Field><Field name="Direccion">Avenida Vespucio 399</Field><Field name="Codigo_postal"/><Field name="Telefono">2 26791629</Field><Field name="Desplazado"/><Field name="Nombre_Oficina">Arauco Maipú</Field><Field name="Latitud">-33.4813538</Field><Field name="Longitud">-70.7518532</Field><Field name="Distancia">1500,8613315639</Field><Field name="Numero_Cajeros">3</Field><Field name="Horario"/><Field name="Nom_Provincia">REGIÓN METROPOLITANA</Field><Field name="Tipo_Oficina">P</Field><Field name="Numero_BancoFacil">1</Field><Field name="Tipo_Cajero"/><Field name="Telefono_Asociado"/></MODULE_RESULT><MODULE_RESULT><Field name="Codigo">337</Field><Field name="Localidad">Peñalolen</Field><Field name="Cod_Oficina">337</Field><Field name="Direccion">Mar Tirreno 3349, Local 7</Field><Field name="Codigo_postal"/><Field name="Telefono">2 26638148</Field><Field name="Desplazado"/><Field name="Nombre_Oficina">Mall Quilín</Field><Field name="Latitud">-33.4862594</Field><Field name="Longitud">-70.576962</Field><Field name="Distancia">1500,9483422696</Field><Field name="Numero_Cajeros">1</Field><Field name="Horario"/><Field name="Nom_Provincia">REGIÓN METROPOLITANA</Field><Field name="Tipo_Oficina">P</Field><Field name="Numero_BancoFacil">0</Field><Field name="Tipo_Cajero"/><Field name="Telefono_Asociado"/></MODULE_RESULT><MODULE_RESULT><Field name="Codigo">23</Field><Field name="Localidad">Cerrillos</Field><Field name="Cod_Oficina">23</Field><Field name="Direccion">Pedro Aguirre Cerda 5819</Field><Field name="Codigo_postal"/><Field name="Telefono">2 22906618</Field><Field name="Desplazado"/><Field name="Nombre_Oficina">Cerrillos</Field><Field name="Latitud">-33.4919922</Field><Field name="Longitud">-70.7037395</Field><Field name="Distancia">1501,7935101412</Field><Field name="Numero_Cajeros">2</Field><Field name="Horario"/><Field name="Nom_Provincia">REGIÓN METROPOLITANA</Field><Field name="Tipo_Oficina">P</Field><Field name="Numero_BancoFacil">1</Field><Field name="Tipo_Cajero"/><Field name="Telefono_Asociado"/></MODULE_RESULT><MODULE_RESULT><Field name="Codigo">39</Field><Field name="Localidad">San Miguel</Field><Field name="Cod_Oficina">39</Field><Field name="Direccion">Avenida Jose Miguel Carrera 5171</Field><Field name="Codigo_postal"/><Field name="Telefono">2 26638505</Field><Field name="Desplazado"/><Field name="Nombre_Oficina">Gran Avenida</Field><Field name="Latitud">-33.500807</Field><Field name="Longitud">-70.6543257</Field><Field name="Distancia">1502,5560404125</Field><Field name="Numero_Cajeros">2</Field><Field name="Horario"/><Field name="Nom_Provincia">REGIÓN METROPOLITANA</Field><Field name="Tipo_Oficina">P</Field><Field name="Numero_BancoFacil">1</Field><Field name="Tipo_Cajero"/><Field name="Telefono_Asociado"/></MODULE_RESULT><MODULE_RESULT><Field name="Codigo">267</Field><Field name="Localidad">Cerrillos</Field><Field name="Cod_Oficina">267</Field><Field name="Direccion">Av. Américo Vespucio Sur 1501</Field><Field name="Codigo_postal"/><Field name="Telefono">2 26638224</Field><Field name="Desplazado"/><Field name="Nombre_Oficina">Mall Plaza Oeste</Field><Field name="Latitud">-33.5</Field><Field name="Longitud">-70.716667</Field><Field name="Distancia">1502,6277515185</Field><Field name="Numero_Cajeros">2</Field><Field name="Horario"/><Field name="Nom_Provincia">REGIÓN METROPOLITANA</Field><Field name="Tipo_Oficina">P</Field><Field name="Numero_BancoFacil">1</Field><Field name="Tipo_Cajero"/><Field name="Telefono_Asociado"/></MODULE_RESULT><MODULE_RESULT><Field name="Codigo">26</Field><Field name="Localidad">Maipú</Field><Field name="Cod_Oficina">26</Field><Field name="Direccion">5 de Abril 98</Field><Field name="Codigo_postal"/><Field name="Telefono">2 22906633</Field><Field name="Desplazado"/><Field name="Nombre_Oficina">Maipú</Field><Field name="Latitud">-33.5106465</Field><Field name="Longitud">-70.7587538</Field><Field name="Distancia">1503,8094385201</Field><Field name="Numero_Cajeros">4</Field><Field name="Horario"/><Field name="Nom_Provincia">REGIÓN METROPOLITANA</Field><Field name="Tipo_Oficina">P</Field><Field name="Numero_BancoFacil">2</Field><Field name="Tipo_Cajero"/><Field name="Telefono_Asociado"/></MODULE_RESULT><MODULE_RESULT><Field name="Codigo">433</Field><Field name="Localidad">La Florida</Field><Field name="Cod_Oficina">433</Field><Field name="Direccion">Avenida Vicuña Mackenna Oriente 7110</Field><Field name="Codigo_postal"/><Field name="Telefono">2 26638175</Field><Field name="Desplazado"/><Field name="Nombre_Oficina">Plaza Vespucio</Field><Field name="Latitud">-33.5205404</Field><Field name="Longitud">-70.5993385</Field><Field name="Distancia">1504,4160860646</Field><Field name="Numero_Cajeros">3</Field><Field name="Horario"/><Field name="Nom_Provincia">REGIÓN METROPOLITANA</Field><Field name="Tipo_Oficina">P</Field><Field name="Numero_BancoFacil">1</Field><Field name="Tipo_Cajero"/><Field name="Telefono_Asociado"/></MODULE_RESULT><MODULE_RESULT><Field name="Codigo">31</Field><Field name="Localidad">La Florida</Field><Field name="Cod_Oficina">31</Field><Field name="Direccion">Avenida Vicuña Mackenna 7438</Field><Field name="Codigo_postal"/><Field name="Telefono">2 26361072</Field><Field name="Desplazado"/><Field name="Nombre_Oficina">La Florida</Field><Field name="Latitud">-33.5217687</Field><Field name="Longitud">-70.5986903</Field><Field name="Distancia">1504,5376847998</Field><Field name="Numero_Cajeros">2</Field><Field name="Horario"/><Field name="Nom_Provincia">REGIÓN METROPOLITANA</Field><Field name="Tipo_Oficina">P</Field><Field name="Numero_BancoFacil">1</Field><Field name="Tipo_Cajero"/><Field name="Telefono_Asociado"/></MODULE_RESULT><MODULE_RESULT><Field name="Codigo">91</Field><Field name="Localidad">La Florida</Field><Field name="Cod_Oficina">91</Field><Field name="Direccion">Avenida La Florida 9261</Field><Field name="Codigo_postal"/><Field name="Telefono">2 26791624</Field><Field name="Desplazado"/><Field name="Nombre_Oficina">Alto La Florida</Field><Field name="Latitud">-33.5373276</Field><Field name="Longitud">-70.5730842</Field><Field name="Distancia">1506,0477932697</Field><Field name="Numero_Cajeros">2</Field><Field name="Horario"/><Field name="Nom_Provincia">REGIÓN METROPOLITANA</Field><Field name="Tipo_Oficina">P</Field><Field name="Numero_BancoFacil">2</Field><Field name="Tipo_Cajero"/><Field name="Telefono_Asociado"/></MODULE_RESULT><MODULE_RESULT><Field name="Codigo">316</Field><Field name="Localidad">Puente Alto</Field><Field name="Cod_Oficina">316</Field><Field name="Direccion">Av. Camilo Henríquez 3962</Field><Field name="Codigo_postal"/><Field name="Telefono">2 26638984</Field><Field name="Desplazado"/><Field name="Nombre_Oficina">Mall Plaza Tobalaba</Field><Field name="Latitud">-33.5662591</Field><Field name="Longitud">-70.5555861</Field><Field name="Distancia">1508,9119873108</Field><Field name="Numero_Cajeros">2</Field><Field name="Horario"/><Field name="Nom_Provincia">REGIÓN METROPOLITANA</Field><Field name="Tipo_Oficina">P</Field><Field name="Numero_BancoFacil">1</Field><Field name="Tipo_Cajero"/><Field name="Telefono_Asociado"/></MODULE_RESULT><MODULE_RESULT><Field name="Codigo">46</Field><Field name="Localidad">San Bernardo</Field><Field name="Cod_Oficina">46</Field><Field name="Direccion">Avda. Colón 718</Field><Field name="Codigo_postal"/><Field name="Telefono">2 26638565</Field><Field name="Desplazado"/><Field name="Nombre_Oficina">San Bernardo</Field><Field name="Latitud">-33.5892479</Field><Field name="Longitud">-70.7055562</Field><Field name="Distancia">1511,520540171</Field><Field name="Numero_Cajeros">2</Field><Field name="Horario"/><Field name="Nom_Provincia">REGIÓN METROPOLITANA</Field><Field name="Tipo_Oficina">P</Field><Field name="Numero_BancoFacil">1</Field><Field name="Tipo_Cajero"/><Field name="Telefono_Asociado"/></MODULE_RESULT><MODULE_RESULT><Field name="Codigo">45</Field><Field name="Localidad">Puente Alto</Field><Field name="Cod_Oficina">45</Field><Field name="Direccion">Avenida Concha y Toro 640</Field><Field name="Codigo_postal"/><Field name="Telefono">2 26638361</Field><Field name="Desplazado"/><Field name="Nombre_Oficina">Puente Alto</Field><Field name="Latitud">-33.6054661</Field><Field name="Longitud">-70.5768128</Field><Field name="Distancia">1512,8669995307</Field><Field name="Numero_Cajeros">2</Field><Field name="Horario"/><Field name="Nom_Provincia">REGIÓN METROPOLITANA</Field><Field name="Tipo_Oficina">P</Field><Field name="Numero_BancoFacil">1</Field><Field name="Tipo_Cajero"/><Field name="Telefono_Asociado"/></MODULE_RESULT><MODULE_RESULT><Field name="Codigo">144</Field><Field name="Localidad">Talagante</Field><Field name="Cod_Oficina">144</Field><Field name="Direccion">O'Higgins 793</Field><Field name="Codigo_postal"/><Field name="Telefono">2 26791686</Field><Field name="Desplazado"/><Field name="Nombre_Oficina">Talagante</Field><Field name="Latitud">-33.664434</Field><Field name="Longitud">-70.92955</Field><Field name="Distancia">1519,7728448225</Field><Field name="Numero_Cajeros">2</Field><Field name="Horario"/><Field name="Nom_Provincia">REGIÓN METROPOLITANA</Field><Field name="Tipo_Oficina">P</Field><Field name="Numero_BancoFacil">1</Field><Field name="Tipo_Cajero"/><Field name="Telefono_Asociado"/></MODULE_RESULT><MODULE_RESULT><Field name="Codigo">376</Field><Field name="Localidad">Buin</Field><Field name="Cod_Oficina">376</Field><Field name="Direccion">Balmaceda 476</Field><Field name="Codigo_postal"/><Field name="Telefono">2 26791870</Field><Field name="Desplazado"/><Field name="Nombre_Oficina">Buin</Field><Field name="Latitud">-33.7325022</Field><Field name="Longitud">-70.7423696</Field><Field name="Distancia">1525,9392025387</Field><Field name="Numero_Cajeros">0</Field><Field name="Horario"/><Field name="Nom_Provincia">REGIÓN METROPOLITANA</Field><Field name="Tipo_Oficina">P</Field><Field name="Numero_BancoFacil">0</Field><Field name="Tipo_Cajero"/><Field name="Telefono_Asociado"/></MODULE_RESULT><MODULE_RESULT><Field name="Codigo">60</Field><Field name="Localidad">Rancagua</Field><Field name="Cod_Oficina">60</Field><Field name="Direccion">Calle O'Carrol 456</Field><Field name="Codigo_postal"/><Field name="Telefono">72-2331354</Field><Field name="Desplazado"/><Field name="Nombre_Oficina">Rancagua</Field><Field name="Latitud">-34.1713036</Field><Field name="Longitud">-70.7417421</Field><Field name="Distancia">1569,8011662838</Field><Field name="Numero_Cajeros">2</Field><Field name="Horario"/><Field name="Nom_Provincia">O'HIGGINS</Field><Field name="Tipo_Oficina">P</Field><Field name="Numero_BancoFacil">1</Field><Field name="Tipo_Cajero"/><Field name="Telefono_Asociado"/></MODULE_RESULT><MODULE_RESULT><Field name="Codigo">126</Field><Field name="Localidad">Rancagua</Field><Field name="Cod_Oficina">126</Field><Field name="Direccion">CARRETERA DEL COBRE PRESIDENTE E.FREI 340</Field><Field name="Codigo_postal"/><Field name="Telefono">72-2331344</Field><Field name="Desplazado"/><Field name="Nombre_Oficina">Rancagua Carretera del Cobre</Field><Field name="Latitud">-34.1923048</Field><Field name="Longitud">-70.6980019</Field><Field name="Distancia">1571,7887492368</Field><Field name="Numero_Cajeros">2</Field><Field name="Horario"/><Field name="Nom_Provincia">O'HIGGINS</Field><Field name="Tipo_Oficina">P</Field><Field name="Numero_BancoFacil">1</Field><Field name="Tipo_Cajero"/><Field name="Telefono_Asociado"/></MODULE_RESULT><MODULE_RESULT><Field name="Codigo">399</Field><Field name="Localidad">Rengo</Field><Field name="Cod_Oficina">399</Field><Field name="Direccion">Carlos Condell 87</Field><Field name="Codigo_postal"/><Field name="Telefono">72-2331386</Field><Field name="Desplazado"/><Field name="Nombre_Oficina">Rengo</Field><Field name="Latitud">-34.4091723</Field><Field name="Longitud">-70.8609131</Field><Field name="Distancia">1593,9407550092</Field><Field name="Numero_Cajeros">1</Field><Field name="Horario"/><Field name="Nom_Provincia">O'HIGGINS</Field><Field name="Tipo_Oficina">P</Field><Field name="Numero_BancoFacil">1</Field><Field name="Tipo_Cajero"/><Field name="Telefono_Asociado"/></MODULE_RESULT><MODULE_RESULT><Field name="Codigo">190</Field><Field name="Localidad">Punta Arenas</Field><Field name="Cod_Oficina">190</Field><Field name="Direccion">21 de Mayo 1133</Field><Field name="Codigo_postal"/><Field name="Telefono">61-2297223</Field><Field name="Desplazado"/><Field name="Nombre_Oficina">Punta Arenas</Field><Field name="Latitud">-53.1635245</Field><Field name="Longitud">-70.9078812</Field><Field name="Distancia">3468,9530147629</Field><Field name="Numero_Cajeros">2</Field><Field name="Horario"/><Field name="Nom_Provincia">MAGALLANES Y DE LA ANTÁRTIDA</Field><Field name="Tipo_Oficina">P</Field><Field name="Numero_BancoFacil">1</Field><Field name="Tipo_Cajero"/><Field name="Telefono_Asociado"/></MODULE_RESULT></DatosZona>